[{"Jref": 1.8, "Jdet": 1.6400000000000001, "Width": 0.5, "Error": 0.15999999999999992, "1Subharmonic": 0.56, "Distance": 1.08, "S/n": 8.790058720012631, "Error2": 0.025599999999999973}, {"Jref": 1.8, "Jdet": 1.8, "Width": 0.5, "Error": 0.0, "1Subharmonic": 0.6, "Distance": 1.2000000000000002, "S/n": 12.225612639185957, "Error2": 0.0}, {"Jref": 1.8, "Jdet": 1.76, "Width": 0.5, "Error": 0.040000000000000036, "1Subharmonic": 0.6, "Distance": 1.1600000000000001, "S/n": 15.703656542818845, "Error2": 0.001600000000000003}, {"Jref": 1.8, "Jdet": 1.6, "Width": 0.5, "Error": 0.19999999999999996, "1Subharmonic": 0.6, "Distance": 1.0, "S/n": 19.308835984797458, "Error2": 0.03999999999999998}, {"Jref": 1.8, "Jdet": 1.8, "Width": 0.5, "Error": 0.0, "1Subharmonic": 0.6, "Distance": 1.2000000000000002, "S/n": 22.497205271052888, "Error2": 0.0}, {"Jref": 1.8, "Jdet": 1.8, "Width": 0.5, "Error": 0.0, "1Subharmonic": 0.6, "Distance": 1.2000000000000002, "S/n": 26.271810319307036, "Error2": 0.0}, {"Jref": 1.8, "Jdet": 1.8, "Width": 0.5, "Error": 0.0, "1Subharmonic": 0.6, "Distance": 1.2000000000000002, "S/n": 29.592178810620705, "Error2": 0.0}, {"Jref": 1.8, "Jdet": 1.84, "Width": 0.5, "Error": -0.040000000000000036, "1Subharmonic": 0.6, "Distance": 1.2400000000000002, "S/n": 33.89766025920009, "Error2": 0.001600000000000003}, {"Jref": 1.8, "Jdet": 1.8, "Width": 0.5, "Error": 0.0, "1Subharmonic": 0.6, "Distance": 1.2000000000000002, "S/n": 37.576706787191036, "Error2": 0.0}, {"Jref": 1.8, "Jdet": 1.84, "Width": 0.5, "Error": -0.040000000000000036, "1Subharmonic": 0.6, "Distance": 1.2400000000000002, "S/n": 40.40057441491303, "Error2": 0.001600000000000003}, {"Jref": 1.8, "Jdet": 1.8, "Width": 0.5, "Error": 0.0, "1Subharmonic": 0.6, "Distance": 1.2000000000000002, "S/n": 43.16334092111072, "Error2": 0.0}, {"Jref": 1.8, "Jdet": 1.8, "Width": 0.5, "Error": 0.0, "1Subharmonic": 0.6, "Distance": 1.2000000000000002, "S/n": 47.2261484183958, "Error2": 0.0}, {"Jref": 1.8, "Jdet": 1.76, "Width": 0.5, "Error": 0.040000000000000036, "1Subharmonic": 0.6, "Distance": 1.1600000000000001, "S/n": 52.137071449505726, "Error2": 0.001600000000000003}, {"Jref": 1.8, "Jdet": 1.8, "Width": 0.5, "Error": 0.0, "1Subharmonic": 0.6, "Distance": 1.2000000000000002, "S/n": 54.8303015333403, "Error2": 0.0}, {"Jref": 1.8, "Jdet": 1.8, "Width": 0.5, "Error": 0.0, "1Subharmonic": 0.6, "Distance": 1.2000000000000002, "S/n": 57.34565166142792, "Error2": 0.0}, {"Jref": 1.8, "Jdet": 1.8, "Width": 0.5, "Error": 0.0, "1Subharmonic": 0.6, "Distance": 1.2000000000000002, "S/n": 62.12559205342751, "Error2": 0.0}, {"Jref": 1.8, "Jdet": 1.8, "Width": 0.5, "Error": 0.0, "1Subharmonic": 0.6, "Distance": 1.2000000000000002, "S/n": 63.22028085268798, "Error2": 0.0}, {"Jref": 1.8, "Jdet": 1.84, "Width": 0.5, "Error": -0.040000000000000036, "1Subharmonic": 0.6, "Distance": 1.2400000000000002, "S/n": 69.82268851064069, "Error2": 0.001600000000000003}, {"Jref": 1.8, "Jdet": 1.84, "Width": 0.5, "Error": -0.040000000000000036, "1Subharmonic": 0.6, "Distance": 1.2400000000000002, "S/n": 70.67760590971444, "Error2": 0.001600000000000003}, {"Jref": 1.8, "Jdet": 1.8, "Width": 0.5, "Error": 0.0, "1Subharmonic": 0.6, "Distance": 1.2000000000000002, "S/n": 76.73157880429234, "Error2": 0.0}, {"Jref": 1.8, "Jdet": 1.8, "Width": 0.5, "Error": 0.0, "1Subharmonic": 0.6, "Distance": 1.2000000000000002, "S/n": 77.53349550395318, "Error2": 0.0}, {"Jref": 1.8, "Jdet": 1.8, "Width": 0.5, "Error": 0.0, "1Subharmonic": 0.6, "Distance": 1.2000000000000002, "S/n": 81.2156143208043, "Error2": 0.0}, {"Jref": 1.8, "Jdet": 1.8, "Width": 0.5, "Error": 0.0, "1Subharmonic": 0.6, "Distance": 1.2000000000000002, "S/n": 85.35229531940801, "Error2": 0.0}, {"Jref": 1.8, "Jdet": 1.8, "Width": 0.5, "Error": 0.0, "1Subharmonic": 0.6, "Distance": 1.2000000000000002, "S/n": 88.98100742764652, "Error2": 0.0}, {"Jref": 1.8, "Jdet": 1.8, "Width": 0.5, "Error": 0.0, "1Subharmonic": 0.6, "Distance": 1.2000000000000002, "S/n": 93.13439592760442, "Error2": 0.0}, {"Jref": 1.8, "Jdet": 1.8, "Width": 0.5, "Error": 0.0, "1Subharmonic": 0.6, "Distance": 1.2000000000000002, "S/n": 96.66954193282203, "Error2": 0.0}, {"Jref": 1.8, "Jdet": 1.8, "Width": 0.5, "Error": 0.0, "1Subharmonic": 0.6, "Distance": 1.2000000000000002, "S/n": 98.41738308240811, "Error2": 0.0}, {"Jref": 1.8, "Jdet": 1.84, "Width": 0.5, "Error": -0.040000000000000036, "1Subharmonic": 0.6, "Distance": 1.2400000000000002, "S/n": 104.07378272094839, "Error2": 0.001600000000000003}, {"Jref": 1.8, "Jdet": 1.8, "Width": 0.5, "Error": 0.0, "1Subharmonic": 0.6, "Distance": 1.2000000000000002, "S/n": 106.32780011294776, "Error2": 0.0}, {"Jref": 1.8, "Jdet": 1.8, "Width": 0.5, "Error": 0.0, "1Subharmonic": 0.6, "Distance": 1.2000000000000002, "S/n": 110.03556570230543, "Error2": 0.0}, {"Jref": 1.8, "Jdet": 1.8, "Width": 0.5, "Error": 0.0, "1Subharmonic": 0.6, "Distance": 1.2000000000000002, "S/n": 116.35307981604686, "Error2": 0.0}, {"Jref": 1.8, "Jdet": 1.8, "Width": 0.5, "Error": 0.0, "1Subharmonic": 0.6, "Distance": 1.2000000000000002, "S/n": 120.36874890708376, "Error2": 0.0}, {"Jref": 1.8, "Jdet": 1.8, "Width": 0.5, "Error": 0.0, "1Subharmonic": 0.6, "Distance": 1.2000000000000002, "S/n": 120.10735817698095, "Error2": 0.0}, {"Jref": 1.8, "Jdet": 1.8, "Width": 0.5, "Error": 0.0, "1Subharmonic": 0.6, "Distance": 1.2000000000000002, "S/n": 128.37658674692216, "Error2": 0.0}, {"Jref": 1.8, "Jdet": 1.8, "Width": 0.5, "Error": 0.0, "1Subharmonic": 0.6, "Distance": 1.2000000000000002, "S/n": 130.00601038834267, "Error2": 0.0}, {"Jref": 1.8, "Jdet": 1.8, "Width": 0.5, "Error": 0.0, "1Subharmonic": 0.6, "Distance": 1.2000000000000002, "S/n": 130.10741241171309, "Error2": 0.0}, {"Jref": 1.8, "Jdet": 1.8, "Width": 0.5, "Error": 0.0, "1Subharmonic": 0.6, "Distance": 1.2000000000000002, "S/n": 136.34722800623757, "Error2": 0.0}, {"Jref": 1.8, "Jdet": 1.8, "Width": 0.5, "Error": 0.0, "1Subharmonic": 0.6, "Distance": 1.2000000000000002, "S/n": 136.71318304578978, "Error2": 0.0}, {"Jref": 1.8, "Jdet": 1.8, "Width": 0.5, "Error": 0.0, "1Subharmonic": 0.6, "Distance": 1.2000000000000002, "S/n": 139.00161512325073, "Error2": 0.0}, {"Jref": 1.8, "Jdet": 1.8, "Width": 0.5, "Error": 0.0, "1Subharmonic": 0.6, "Distance": 1.2000000000000002, "S/n": 144.59127765980455, "Error2": 0.0}, {"Jref": 1.8, "Jdet": 1.8, "Width": 0.5, "Error": 0.0, "1Subharmonic": 0.6, "Distance": 1.2000000000000002, "S/n": 147.83509930903114, "Error2": 0.0}, {"Jref": 1.8, "Jdet": 1.8, "Width": 0.5, "Error": 0.0, "1Subharmonic": 0.6, "Distance": 1.2000000000000002, "S/n": 152.47621045966986, "Error2": 0.0}, {"Jref": 1.8, "Jdet": 1.8, "Width": 0.5, "Error": 0.0, "1Subharmonic": 0.6, "Distance": 1.2000000000000002, "S/n": 156.07370045020954, "Error2": 0.0}, {"Jref": 1.8, "Jdet": 1.8, "Width": 0.5, "Error": 0.0, "1Subharmonic": 0.6, "Distance": 1.2000000000000002, "S/n": 162.17272447662648, "Error2": 0.0}, {"Jref": 1.8, "Jdet": 1.8, "Width": 0.5, "Error": 0.0, "1Subharmonic": 0.6, "Distance": 1.2000000000000002, "S/n": 163.95257075516167, "Error2": 0.0}, {"Jref": 1.8, "Jdet": 1.8, "Width": 0.5, "Error": 0.0, "1Subharmonic": 0.6, "Distance": 1.2000000000000002, "S/n": 168.79259001402727, "Error2": 0.0}, {"Jref": 1.8, "Jdet": 1.8, "Width": 0.5, "Error": 0.0, "1Subharmonic": 0.6, "Distance": 1.2000000000000002, "S/n": 166.31973722170622, "Error2": 0.0}, {"Jref": 1.8, "Jdet": 1.8, "Width": 0.5, "Error": 0.0, "1Subharmonic": 0.6, "Distance": 1.2000000000000002, "S/n": 175.19211473652362, "Error2": 0.0}, {"Jref": 1.8, "Jdet": 1.8, "Width": 0.5, "Error": 0.0, "1Subharmonic": 0.6, "Distance": 1.2000000000000002, "S/n": 179.98975891871396, "Error2": 0.0}, {"Jref": 1.8, "Jdet": 1.8, "Width": 0.5, "Error": 0.0, "1Subharmonic": 0.6, "Distance": 1.2000000000000002, "S/n": 180.4796832709081, "Error2": 0.0}, {"Jref": 1.8, "Jdet": 1.8, "Width": 0.5, "Error": 0.0, "1Subharmonic": 0.6, "Distance": 1.2000000000000002, "S/n": 181.4782471265425, "Error2": 0.0}, {"Jref": 1.8, "Jdet": 1.8, "Width": 0.5, "Error": 0.0, "1Subharmonic": 0.6, "Distance": 1.2000000000000002, "S/n": 185.74569166676358, "Error2": 0.0}, {"Jref": 1.8, "Jdet": 1.8, "Width": 0.5, "Error": 0.0, "1Subharmonic": 0.6, "Distance": 1.2000000000000002, "S/n": 190.07931012508945, "Error2": 0.0}, {"Jref": 1.8, "Jdet": 1.8, "Width": 0.5, "Error": 0.0, "1Subharmonic": 0.6, "Distance": 1.2000000000000002, "S/n": 193.83752839408965, "Error2": 0.0}, {"Jref": 1.8, "Jdet": 1.8, "Width": 0.5, "Error": 0.0, "1Subharmonic": 0.6, "Distance": 1.2000000000000002, "S/n": 207.6488343468219, "Error2": 0.0}, {"Jref": 1.8, "Jdet": 1.8, "Width": 0.5, "Error": 0.0, "1Subharmonic": 0.6, "Distance": 1.2000000000000002, "S/n": 207.4525810653362, "Error2": 0.0}, {"Jref": 1.8, "Jdet": 1.8, "Width": 0.5, "Error": 0.0, "1Subharmonic": 0.6, "Distance": 1.2000000000000002, "S/n": 208.71485316285933, "Error2": 0.0}, {"Jref": 1.8, "Jdet": 1.8, "Width": 0.5, "Error": 0.0, "1Subharmonic": 0.6, "Distance": 1.2000000000000002, "S/n": 215.06058435789635, "Error2": 0.0}, {"Jref": 1.8, "Jdet": 1.8, "Width": 0.5, "Error": 0.0, "1Subharmonic": 0.6, "Distance": 1.2000000000000002, "S/n": 216.74250698844014, "Error2": 0.0}, {"Jref": 1.8, "Jdet": 1.8, "Width": 0.5, "Error": 0.0, "1Subharmonic": 0.6, "Distance": 1.2000000000000002, "S/n": 215.24219726132523, "Error2": 0.0}, {"Jref": 1.8, "Jdet": 1.8, "Width": 0.5, "Error": 0.0, "1Subharmonic": 0.6, "Distance": 1.2000000000000002, "S/n": 222.26904099140845, "Error2": 0.0}, {"Jref": 1.8, "Jdet": 1.8, "Width": 0.5, "Error": 0.0, "1Subharmonic": 0.6, "Distance": 1.2000000000000002, "S/n": 224.66371207248972, "Error2": 0.0}, {"Jref": 1.8, "Jdet": 1.8, "Width": 0.5, "Error": 0.0, "1Subharmonic": 0.6, "Distance": 1.2000000000000002, "S/n": 227.63159854122154, "Error2": 0.0}, {"Jref": 1.8, "Jdet": 1.8, "Width": 0.5, "Error": 0.0, "1Subharmonic": 0.6, "Distance": 1.2000000000000002, "S/n": 232.5113439583174, "Error2": 0.0}, {"Jref": 1.8, "Jdet": 1.8, "Width": 0.5, "Error": 0.0, "1Subharmonic": 0.6, "Distance": 1.2000000000000002, "S/n": 242.3565948609136, "Error2": 0.0}, {"Jref": 1.8, "Jdet": 1.8, "Width": 0.5, "Error": 0.0, "1Subharmonic": 0.6, "Distance": 1.2000000000000002, "S/n": 239.6272295025562, "Error2": 0.0}, {"Jref": 1.8, "Jdet": 1.8, "Width": 0.5, "Error": 0.0, "1Subharmonic": 0.6, "Distance": 1.2000000000000002, "S/n": 246.69225974819275, "Error2": 0.0}, {"Jref": 1.8, "Jdet": 1.8, "Width": 0.5, "Error": 0.0, "1Subharmonic": 0.6, "Distance": 1.2000000000000002, "S/n": 240.55126683919045, "Error2": 0.0}, {"Jref": 1.8, "Jdet": 1.8, "Width": 0.5, "Error": 0.0, "1Subharmonic": 0.6, "Distance": 1.2000000000000002, "S/n": 245.11698110209772, "Error2": 0.0}, {"Jref": 1.8, "Jdet": 1.8, "Width": 0.5, "Error": 0.0, "1Subharmonic": 0.6, "Distance": 1.2000000000000002, "S/n": 249.02265663425445, "Error2": 0.0}, {"Jref": 1.8, "Jdet": 1.8, "Width": 0.5, "Error": 0.0, "1Subharmonic": 0.6, "Distance": 1.2000000000000002, "S/n": 253.63285380458098, "Error2": 0.0}, {"Jref": 1.8, "Jdet": 1.8, "Width": 0.5, "Error": 0.0, "1Subharmonic": 0.6, "Distance": 1.2000000000000002, "S/n": 263.9761451933972, "Error2": 0.0}, {"Jref": 1.8, "Jdet": 1.8, "Width": 0.5, "Error": 0.0, "1Subharmonic": 0.6, "Distance": 1.2000000000000002, "S/n": 265.422278778969, "Error2": 0.0}, {"Jref": 1.8, "Jdet": 1.8, "Width": 0.5, "Error": 0.0, "1Subharmonic": 0.6, "Distance": 1.2000000000000002, "S/n": 265.9845766513911, "Error2": 0.0}, {"Jref": 1.8, "Jdet": 1.8, "Width": 0.5, "Error": 0.0, "1Subharmonic": 0.6, "Distance": 1.2000000000000002, "S/n": 269.15956575391016, "Error2": 0.0}, {"Jref": 1.8, "Jdet": 1.8, "Width": 0.5, "Error": 0.0, "1Subharmonic": 0.6, "Distance": 1.2000000000000002, "S/n": 274.4553902437916, "Error2": 0.0}, {"Jref": 1.8, "Jdet": 1.8, "Width": 0.5, "Error": 0.0, "1Subharmonic": 0.6, "Distance": 1.2000000000000002, "S/n": 275.71096258306517, "Error2": 0.0}, {"Jref": 1.8, "Jdet": 1.8, "Width": 0.5, "Error": 0.0, "1Subharmonic": 0.6, "Distance": 1.2000000000000002, "S/n": 279.42879369937657, "Error2": 0.0}, {"Jref": 1.8, "Jdet": 1.8, "Width": 0.5, "Error": 0.0, "1Subharmonic": 0.6, "Distance": 1.2000000000000002, "S/n": 281.33426836165273, "Error2": 0.0}, {"Jref": 1.8, "Jdet": 1.8, "Width": 0.5, "Error": 0.0, "1Subharmonic": 0.6, "Distance": 1.2000000000000002, "S/n": 290.9728374453788, "Error2": 0.0}, {"Jref": 1.8, "Jdet": 1.8, "Width": 0.5, "Error": 0.0, "1Subharmonic": 0.6, "Distance": 1.2000000000000002, "S/n": 291.4003471176989, "Error2": 0.0}, {"Jref": 1.8, "Jdet": 1.8, "Width": 0.5, "Error": 0.0, "1Subharmonic": 0.6, "Distance": 1.2000000000000002, "S/n": 295.838297573087, "Error2": 0.0}, {"Jref": 1.8, "Jdet": 1.8, "Width": 0.5, "Error": 0.0, "1Subharmonic": 0.6, "Distance": 1.2000000000000002, "S/n": 296.4299415333391, "Error2": 0.0}, {"Jref": 1.8, "Jdet": 1.8, "Width": 0.5, "Error": 0.0, "1Subharmonic": 0.6, "Distance": 1.2000000000000002, "S/n": 306.5389950577491, "Error2": 0.0}, {"Jref": 1.8, "Jdet": 1.8, "Width": 0.5, "Error": 0.0, "1Subharmonic": 0.6, "Distance": 1.2000000000000002, "S/n": 303.314580822183, "Error2": 0.0}, {"Jref": 1.8, "Jdet": 1.8, "Width": 0.5, "Error": 0.0, "1Subharmonic": 0.6, "Distance": 1.2000000000000002, "S/n": 313.37708542804927, "Error2": 0.0}, {"Jref": 1.8, "Jdet": 1.8, "Width": 0.5, "Error": 0.0, "1Subharmonic": 0.6, "Distance": 1.2000000000000002, "S/n": 309.32467148499893, "Error2": 0.0}, {"Jref": 1.8, "Jdet": 1.8, "Width": 0.5, "Error": 0.0, "1Subharmonic": 0.6, "Distance": 1.2000000000000002, "S/n": 318.6260083704593, "Error2": 0.0}, {"Jref": 1.8, "Jdet": 1.8, "Width": 0.5, "Error": 0.0, "1Subharmonic": 0.6, "Distance": 1.2000000000000002, "S/n": 307.0481725450511, "Error2": 0.0}, {"Jref": 1.8, "Jdet": 1.8, "Width": 0.5, "Error": 0.0, "1Subharmonic": 0.6, "Distance": 1.2000000000000002, "S/n": 313.08358419250436, "Error2": 0.0}, {"Jref": 1.8, "Jdet": 1.8, "Width": 0.5, "Error": 0.0, "1Subharmonic": 0.6, "Distance": 1.2000000000000002, "S/n": 334.6108238887301, "Error2": 0.0}, {"Jref": 1.8, "Jdet": 1.8, "Width": 0.5, "Error": 0.0, "1Subharmonic": 0.6, "Distance": 1.2000000000000002, "S/n": 333.6656556938541, "Error2": 0.0}, {"Jref": 1.8, "Jdet": 1.8, "Width": 0.5, "Error": 0.0, "1Subharmonic": 0.6, "Distance": 1.2000000000000002, "S/n": 324.4479557483778, "Error2": 0.0}, {"Jref": 1.8, "Jdet": 1.8, "Width": 0.5, "Error": 0.0, "1Subharmonic": 0.6, "Distance": 1.2000000000000002, "S/n": 335.97168104997604, "Error2": 0.0}, {"Jref": 1.8, "Jdet": 1.8, "Width": 0.5, "Error": 0.0, "1Subharmonic": 0.6, "Distance": 1.2000000000000002, "S/n": 336.747215389756, "Error2": 0.0}, {"Jref": 1.8, "Jdet": 1.8, "Width": 0.5, "Error": 0.0, "1Subharmonic": 0.6, "Distance": 1.2000000000000002, "S/n": 341.5093935431301, "Error2": 0.0}, {"Jref": 1.8, "Jdet": 1.8, "Width": 0.5, "Error": 0.0, "1Subharmonic": 0.6, "Distance": 1.2000000000000002, "S/n": 352.5129715046315, "Error2": 0.0}, {"Jref": 1.8, "Jdet": 1.8, "Width": 0.5, "Error": 0.0, "1Subharmonic": 0.6, "Distance": 1.2000000000000002, "S/n": 356.3954684680842, "Error2": 0.0}, {"Jref": 1.8, "Jdet": 1.8, "Width": 0.5, "Error": 0.0, "1Subharmonic": 0.6, "Distance": 1.2000000000000002, "S/n": 348.282224584044, "Error2": 0.0}, {"Jref": 1.8, "Jdet": 1.8, "Width": 0.5, "Error": 0.0, "1Subharmonic": 0.6, "Distance": 1.2000000000000002, "S/n": 365.63045459005195, "Error2": 0.0}, {"Jref": 1.8, "Jdet": 1.8, "Width": 0.5, "Error": 0.0, "1Subharmonic": 0.6, "Distance": 1.2000000000000002, "S/n": 361.80248776917654, "Error2": 0.0}, {"Jref": 1.8, "Jdet": 1.8, "Width": 0.5, "Error": 0.0, "1Subharmonic": 0.6, "Distance": 1.2000000000000002, "S/n": 356.5746262363142, "Error2": 0.0}, {"Jref": 1.8, "Jdet": 1.8, "Width": 0.5, "Error": 0.0, "1Subharmonic": 0.6, "Distance": 1.2000000000000002, "S/n": 363.13622418436285, "Error2": 0.0}, {"Jref": 1.8, "Jdet": 1.8, "Width": 0.5, "Error": 0.0, "1Subharmonic": 0.6, "Distance": 1.2000000000000002, "S/n": 378.79053229958816, "Error2": 0.0}, {"Jref": 1.8, "Jdet": 1.8, "Width": 0.5, "Error": 0.0, "1Subharmonic": 0.6, "Distance": 1.2000000000000002, "S/n": 376.67900086964875, "Error2": 0.0}, {"Jref": 1.8, "Jdet": 1.8, "Width": 0.5, "Error": 0.0, "1Subharmonic": 0.6, "Distance": 1.2000000000000002, "S/n": 380.3825211529015, "Error2": 0.0}, {"Jref": 1.8, "Jdet": 1.8, "Width": 0.5, "Error": 0.0, "1Subharmonic": 0.6, "Distance": 1.2000000000000002, "S/n": 385.0426065086503, "Error2": 0.0}, {"Jref": 1.8, "Jdet": 1.8, "Width": 0.5, "Error": 0.0, "1Subharmonic": 0.6, "Distance": 1.2000000000000002, "S/n": 387.2237729554929, "Error2": 0.0}, {"Jref": 1.8, "Jdet": 1.8, "Width": 0.5, "Error": 0.0, "1Subharmonic": 0.6, "Distance": 1.2000000000000002, "S/n": 392.3975209525084, "Error2": 0.0}, {"Jref": 1.8, "Jdet": 1.8, "Width": 0.5, "Error": 0.0, "1Subharmonic": 0.6, "Distance": 1.2000000000000002, "S/n": 398.7012160228066, "Error2": 0.0}, {"Jref": 1.8, "Jdet": 1.8, "Width": 0.5, "Error": 0.0, "1Subharmonic": 0.6, "Distance": 1.2000000000000002, "S/n": 400.7793324096612, "Error2": 0.0}, {"Jref": 1.8, "Jdet": 1.8, "Width": 0.5, "Error": 0.0, "1Subharmonic": 0.6, "Distance": 1.2000000000000002, "S/n": 398.51050555265687, "Error2": 0.0}, {"Jref": 1.8, "Jdet": 1.8, "Width": 0.5, "Error": 0.0, "1Subharmonic": 0.6, "Distance": 1.2000000000000002, "S/n": 400.08307801261464, "Error2": 0.0}, {"Jref": 1.8, "Jdet": 1.8, "Width": 0.5, "Error": 0.0, "1Subharmonic": 0.6, "Distance": 1.2000000000000002, "S/n": 412.4067351313486, "Error2": 0.0}, {"Jref": 1.8, "Jdet": 1.8, "Width": 0.5, "Error": 0.0, "1Subharmonic": 0.6, "Distance": 1.2000000000000002, "S/n": 407.39132751845665, "Error2": 0.0}, {"Jref": 1.8, "Jdet": 1.8, "Width": 0.5, "Error": 0.0, "1Subharmonic": 0.6, "Distance": 1.2000000000000002, "S/n": 407.4975056686982, "Error2": 0.0}, {"Jref": 1.8, "Jdet": 1.8, "Width": 0.5, "Error": 0.0, "1Subharmonic": 0.6, "Distance": 1.2000000000000002, "S/n": 417.65814789541577, "Error2": 0.0}, {"Jref": 1.8, "Jdet": 1.8, "Width": 0.5, "Error": 0.0, "1Subharmonic": 0.6, "Distance": 1.2000000000000002, "S/n": 417.1254400422015, "Error2": 0.0}, {"Jref": 1.8, "Jdet": 1.8, "Width": 0.5, "Error": 0.0, "1Subharmonic": 0.6, "Distance": 1.2000000000000002, "S/n": 424.4634042768204, "Error2": 0.0}, {"Jref": 1.8, "Jdet": 1.8, "Width": 0.5, "Error": 0.0, "1Subharmonic": 0.6, "Distance": 1.2000000000000002, "S/n": 432.30656999570994, "Error2": 0.0}, {"Jref": 1.8, "Jdet": 1.8, "Width": 0.5, "Error": 0.0, "1Subharmonic": 0.6, "Distance": 1.2000000000000002, "S/n": 438.32711184463807, "Error2": 0.0}, {"Jref": 1.8, "Jdet": 1.8, "Width": 0.5, "Error": 0.0, "1Subharmonic": 0.6, "Distance": 1.2000000000000002, "S/n": 428.3036337792935, "Error2": 0.0}, {"Jref": 1.8, "Jdet": 1.8, "Width": 0.5, "Error": 0.0, "1Subharmonic": 0.6, "Distance": 1.2000000000000002, "S/n": 444.4496102788715, "Error2": 0.0}, {"Jref": 1.8, "Jdet": 1.8, "Width": 0.5, "Error": 0.0, "1Subharmonic": 0.6, "Distance": 1.2000000000000002, "S/n": 453.2674163155305, "Error2": 0.0}, {"Jref": 1.8, "Jdet": 1.8, "Width": 0.5, "Error": 0.0, "1Subharmonic": 0.6, "Distance": 1.2000000000000002, "S/n": 443.0350331050003, "Error2": 0.0}, {"Jref": 1.8, "Jdet": 1.8, "Width": 0.5, "Error": 0.0, "1Subharmonic": 0.6, "Distance": 1.2000000000000002, "S/n": 452.39236529411266, "Error2": 0.0}, {"Jref": 1.8, "Jdet": 1.8, "Width": 0.5, "Error": 0.0, "1Subharmonic": 0.6, "Distance": 1.2000000000000002, "S/n": 468.5706385384679, "Error2": 0.0}, {"Jref": 1.8, "Jdet": 1.8, "Width": 0.5, "Error": 0.0, "1Subharmonic": 0.6, "Distance": 1.2000000000000002, "S/n": 447.56746255319985, "Error2": 0.0}, {"Jref": 1.8, "Jdet": 1.8, "Width": 0.5, "Error": 0.0, "1Subharmonic": 0.6, "Distance": 1.2000000000000002, "S/n": 459.7786814554419, "Error2": 0.0}, {"Jref": 1.8, "Jdet": 1.8, "Width": 0.5, "Error": 0.0, "1Subharmonic": 0.6, "Distance": 1.2000000000000002, "S/n": 464.930122510942, "Error2": 0.0}, {"Jref": 1.8, "Jdet": 1.8, "Width": 0.5, "Error": 0.0, "1Subharmonic": 0.6, "Distance": 1.2000000000000002, "S/n": 453.27085770859935, "Error2": 0.0}, {"Jref": 1.8, "Jdet": 1.8, "Width": 0.5, "Error": 0.0, "1Subharmonic": 0.6, "Distance": 1.2000000000000002, "S/n": 468.159649647553, "Error2": 0.0}, {"Jref": 1.8, "Jdet": 1.8, "Width": 0.5, "Error": 0.0, "1Subharmonic": 0.6, "Distance": 1.2000000000000002, "S/n": 460.5910913807978, "Error2": 0.0}, {"Jref": 1.8, "Jdet": 1.8, "Width": 0.5, "Error": 0.0, "1Subharmonic": 0.6, "Distance": 1.2000000000000002, "S/n": 480.5976589752709, "Error2": 0.0}, {"Jref": 1.8, "Jdet": 1.8, "Width": 0.5, "Error": 0.0, "1Subharmonic": 0.6, "Distance": 1.2000000000000002, "S/n": 487.6398170715356, "Error2": 0.0}, {"Jref": 1.8, "Jdet": 1.8, "Width": 0.5, "Error": 0.0, "1Subharmonic": 0.6, "Distance": 1.2000000000000002, "S/n": 483.4840191583972, "Error2": 0.0}, {"Jref": 1.8, "Jdet": 1.8, "Width": 0.5, "Error": 0.0, "1Subharmonic": 0.6, "Distance": 1.2000000000000002, "S/n": 496.97606763023936, "Error2": 0.0}, {"Jref": 1.8, "Jdet": 1.8, "Width": 0.5, "Error": 0.0, "1Subharmonic": 0.6, "Distance": 1.2000000000000002, "S/n": 496.56695593000507, "Error2": 0.0}, {"Jref": 1.8, "Jdet": 1.8, "Width": 0.5, "Error": 0.0, "1Subharmonic": 0.6, "Distance": 1.2000000000000002, "S/n": 500.4764682578723, "Error2": 0.0}, {"Jref": 1.8, "Jdet": 1.8, "Width": 0.5, "Error": 0.0, "1Subharmonic": 0.6, "Distance": 1.2000000000000002, "S/n": 505.3166123701431, "Error2": 0.0}, {"Jref": 1.8, "Jdet": 1.8, "Width": 0.5, "Error": 0.0, "1Subharmonic": 0.6, "Distance": 1.2000000000000002, "S/n": 503.1092972517166, "Error2": 0.0}, {"Jref": 1.8, "Jdet": 1.8, "Width": 0.5, "Error": 0.0, "1Subharmonic": 0.6, "Distance": 1.2000000000000002, "S/n": 501.82344035576904, "Error2": 0.0}, {"Jref": 1.8, "Jdet": 1.8, "Width": 0.5, "Error": 0.0, "1Subharmonic": 0.6, "Distance": 1.2000000000000002, "S/n": 514.8103257782453, "Error2": 0.0}, {"Jref": 1.8, "Jdet": 1.8, "Width": 0.5, "Error": 0.0, "1Subharmonic": 0.6, "Distance": 1.2000000000000002, "S/n": 513.8865775991649, "Error2": 0.0}, {"Jref": 1.8, "Jdet": 1.8, "Width": 0.5, "Error": 0.0, "1Subharmonic": 0.6, "Distance": 1.2000000000000002, "S/n": 520.0199891740269, "Error2": 0.0}, {"Jref": 1.8, "Jdet": 1.8, "Width": 0.5, "Error": 0.0, "1Subharmonic": 0.6, "Distance": 1.2000000000000002, "S/n": 507.4053911939333, "Error2": 0.0}, {"Jref": 1.8, "Jdet": 1.8, "Width": 0.5, "Error": 0.0, "1Subharmonic": 0.6, "Distance": 1.2000000000000002, "S/n": 523.0697228144733, "Error2": 0.0}, {"Jref": 1.8, "Jdet": 1.8, "Width": 0.5, "Error": 0.0, "1Subharmonic": 0.6, "Distance": 1.2000000000000002, "S/n": 535.7241821471766, "Error2": 0.0}]