[{"Jref": 1.2, "Jdet": 0.76, "Width": 0.6, "Error": 0.43999999999999995, "1Subharmonic": 0.24, "Distance": 0.52, "S/n": 7.768754409184416, "Error2": 0.19359999999999997}, {"Jref": 1.2, "Jdet": 1.16, "Width": 0.6, "Error": 0.040000000000000036, "1Subharmonic": 0.4, "Distance": 0.7599999999999999, "S/n": 10.647970809670023, "Error2": 0.001600000000000003}, {"Jref": 1.2, "Jdet": 1.2, "Width": 0.6, "Error": 0.0, "1Subharmonic": 0.4, "Distance": 0.7999999999999999, "S/n": 13.48479449647406, "Error2": 0.0}, {"Jref": 1.2, "Jdet": 1.12, "Width": 0.6, "Error": 0.07999999999999985, "1Subharmonic": 0.4, "Distance": 0.7200000000000001, "S/n": 16.580079791305774, "Error2": 0.006399999999999976}, {"Jref": 1.2, "Jdet": 1.2, "Width": 0.6, "Error": 0.0, "1Subharmonic": 0.4, "Distance": 0.7999999999999999, "S/n": 19.40036446766988, "Error2": 0.0}, {"Jref": 1.2, "Jdet": 1.16, "Width": 0.6, "Error": 0.040000000000000036, "1Subharmonic": 0.36, "Distance": 0.7999999999999999, "S/n": 23.3044712795579, "Error2": 0.001600000000000003}, {"Jref": 1.2, "Jdet": 1.2, "Width": 0.6, "Error": 0.0, "1Subharmonic": 0.4, "Distance": 0.7999999999999999, "S/n": 26.465044958979423, "Error2": 0.0}, {"Jref": 1.2, "Jdet": 1.12, "Width": 0.6, "Error": 0.07999999999999985, "1Subharmonic": 0.4, "Distance": 0.7200000000000001, "S/n": 28.353518953725292, "Error2": 0.006399999999999976}, {"Jref": 1.2, "Jdet": 1.24, "Width": 0.6, "Error": -0.040000000000000036, "1Subharmonic": 0.4, "Distance": 0.84, "S/n": 32.77106107331094, "Error2": 0.001600000000000003}, {"Jref": 1.2, "Jdet": 1.2, "Width": 0.6, "Error": 0.0, "1Subharmonic": 0.4, "Distance": 0.7999999999999999, "S/n": 35.870275136402675, "Error2": 0.0}, {"Jref": 1.2, "Jdet": 1.2, "Width": 0.6, "Error": 0.0, "1Subharmonic": 0.4, "Distance": 0.7999999999999999, "S/n": 38.664508042767295, "Error2": 0.0}, {"Jref": 1.2, "Jdet": 1.2, "Width": 0.6, "Error": 0.0, "1Subharmonic": 0.4, "Distance": 0.7999999999999999, "S/n": 41.20789423579164, "Error2": 0.0}, {"Jref": 1.2, "Jdet": 1.16, "Width": 0.6, "Error": 0.040000000000000036, "1Subharmonic": 0.4, "Distance": 0.7599999999999999, "S/n": 44.240722096561896, "Error2": 0.001600000000000003}, {"Jref": 1.2, "Jdet": 1.2, "Width": 0.6, "Error": 0.0, "1Subharmonic": 0.4, "Distance": 0.7999999999999999, "S/n": 46.817009381931534, "Error2": 0.0}, {"Jref": 1.2, "Jdet": 1.2, "Width": 0.6, "Error": 0.0, "1Subharmonic": 0.4, "Distance": 0.7999999999999999, "S/n": 51.6175521372237, "Error2": 0.0}, {"Jref": 1.2, "Jdet": 1.2, "Width": 0.6, "Error": 0.0, "1Subharmonic": 0.4, "Distance": 0.7999999999999999, "S/n": 54.2997895115012, "Error2": 0.0}, {"Jref": 1.2, "Jdet": 1.16, "Width": 0.6, "Error": 0.040000000000000036, "1Subharmonic": 0.4, "Distance": 0.7599999999999999, "S/n": 55.95604353614107, "Error2": 0.001600000000000003}, {"Jref": 1.2, "Jdet": 1.2, "Width": 0.6, "Error": 0.0, "1Subharmonic": 0.4, "Distance": 0.7999999999999999, "S/n": 57.82070674478455, "Error2": 0.0}, {"Jref": 1.2, "Jdet": 1.2, "Width": 0.6, "Error": 0.0, "1Subharmonic": 0.4, "Distance": 0.7999999999999999, "S/n": 63.29286686006791, "Error2": 0.0}, {"Jref": 1.2, "Jdet": 1.16, "Width": 0.6, "Error": 0.040000000000000036, "1Subharmonic": 0.4, "Distance": 0.7599999999999999, "S/n": 65.1345935112619, "Error2": 0.001600000000000003}, {"Jref": 1.2, "Jdet": 1.2, "Width": 0.6, "Error": 0.0, "1Subharmonic": 0.4, "Distance": 0.7999999999999999, "S/n": 68.01710879633319, "Error2": 0.0}, {"Jref": 1.2, "Jdet": 1.2, "Width": 0.6, "Error": 0.0, "1Subharmonic": 0.4, "Distance": 0.7999999999999999, "S/n": 71.37246002985475, "Error2": 0.0}, {"Jref": 1.2, "Jdet": 1.2, "Width": 0.6, "Error": 0.0, "1Subharmonic": 0.4, "Distance": 0.7999999999999999, "S/n": 74.77337544911381, "Error2": 0.0}, {"Jref": 1.2, "Jdet": 1.2, "Width": 0.6, "Error": 0.0, "1Subharmonic": 0.4, "Distance": 0.7999999999999999, "S/n": 77.90547632845436, "Error2": 0.0}, {"Jref": 1.2, "Jdet": 1.2, "Width": 0.6, "Error": 0.0, "1Subharmonic": 0.4, "Distance": 0.7999999999999999, "S/n": 81.95075461342394, "Error2": 0.0}, {"Jref": 1.2, "Jdet": 1.2, "Width": 0.6, "Error": 0.0, "1Subharmonic": 0.4, "Distance": 0.7999999999999999, "S/n": 85.30918936959506, "Error2": 0.0}, {"Jref": 1.2, "Jdet": 1.2, "Width": 0.6, "Error": 0.0, "1Subharmonic": 0.4, "Distance": 0.7999999999999999, "S/n": 85.94914308395299, "Error2": 0.0}, {"Jref": 1.2, "Jdet": 1.2, "Width": 0.6, "Error": 0.0, "1Subharmonic": 0.4, "Distance": 0.7999999999999999, "S/n": 88.89589406499206, "Error2": 0.0}, {"Jref": 1.2, "Jdet": 1.2, "Width": 0.6, "Error": 0.0, "1Subharmonic": 0.4, "Distance": 0.7999999999999999, "S/n": 93.64731504020855, "Error2": 0.0}, {"Jref": 1.2, "Jdet": 1.2, "Width": 0.6, "Error": 0.0, "1Subharmonic": 0.4, "Distance": 0.7999999999999999, "S/n": 96.65749861927752, "Error2": 0.0}, {"Jref": 1.2, "Jdet": 1.2, "Width": 0.6, "Error": 0.0, "1Subharmonic": 0.4, "Distance": 0.7999999999999999, "S/n": 98.77694636046645, "Error2": 0.0}, {"Jref": 1.2, "Jdet": 1.2, "Width": 0.6, "Error": 0.0, "1Subharmonic": 0.4, "Distance": 0.7999999999999999, "S/n": 102.96809396769112, "Error2": 0.0}, {"Jref": 1.2, "Jdet": 1.2, "Width": 0.6, "Error": 0.0, "1Subharmonic": 0.4, "Distance": 0.7999999999999999, "S/n": 105.15640595124154, "Error2": 0.0}, {"Jref": 1.2, "Jdet": 1.2, "Width": 0.6, "Error": 0.0, "1Subharmonic": 0.4, "Distance": 0.7999999999999999, "S/n": 109.36339344496999, "Error2": 0.0}, {"Jref": 1.2, "Jdet": 1.2, "Width": 0.6, "Error": 0.0, "1Subharmonic": 0.4, "Distance": 0.7999999999999999, "S/n": 110.96725605813447, "Error2": 0.0}, {"Jref": 1.2, "Jdet": 1.2, "Width": 0.6, "Error": 0.0, "1Subharmonic": 0.4, "Distance": 0.7999999999999999, "S/n": 111.58801561933657, "Error2": 0.0}, {"Jref": 1.2, "Jdet": 1.2, "Width": 0.6, "Error": 0.0, "1Subharmonic": 0.4, "Distance": 0.7999999999999999, "S/n": 118.68676735915484, "Error2": 0.0}, {"Jref": 1.2, "Jdet": 1.2, "Width": 0.6, "Error": 0.0, "1Subharmonic": 0.4, "Distance": 0.7999999999999999, "S/n": 119.29582530354816, "Error2": 0.0}, {"Jref": 1.2, "Jdet": 1.2, "Width": 0.6, "Error": 0.0, "1Subharmonic": 0.4, "Distance": 0.7999999999999999, "S/n": 124.81951759950289, "Error2": 0.0}, {"Jref": 1.2, "Jdet": 1.2, "Width": 0.6, "Error": 0.0, "1Subharmonic": 0.4, "Distance": 0.7999999999999999, "S/n": 126.80063065318411, "Error2": 0.0}, {"Jref": 1.2, "Jdet": 1.2, "Width": 0.6, "Error": 0.0, "1Subharmonic": 0.4, "Distance": 0.7999999999999999, "S/n": 127.84922635778312, "Error2": 0.0}, {"Jref": 1.2, "Jdet": 1.2, "Width": 0.6, "Error": 0.0, "1Subharmonic": 0.4, "Distance": 0.7999999999999999, "S/n": 134.29171866446978, "Error2": 0.0}, {"Jref": 1.2, "Jdet": 1.2, "Width": 0.6, "Error": 0.0, "1Subharmonic": 0.4, "Distance": 0.7999999999999999, "S/n": 137.81702289673237, "Error2": 0.0}, {"Jref": 1.2, "Jdet": 1.2, "Width": 0.6, "Error": 0.0, "1Subharmonic": 0.4, "Distance": 0.7999999999999999, "S/n": 142.2537266759781, "Error2": 0.0}, {"Jref": 1.2, "Jdet": 1.2, "Width": 0.6, "Error": 0.0, "1Subharmonic": 0.4, "Distance": 0.7999999999999999, "S/n": 145.10683425842018, "Error2": 0.0}, {"Jref": 1.2, "Jdet": 1.2, "Width": 0.6, "Error": 0.0, "1Subharmonic": 0.4, "Distance": 0.7999999999999999, "S/n": 142.7738542775441, "Error2": 0.0}, {"Jref": 1.2, "Jdet": 1.2, "Width": 0.6, "Error": 0.0, "1Subharmonic": 0.4, "Distance": 0.7999999999999999, "S/n": 149.45757395876123, "Error2": 0.0}, {"Jref": 1.2, "Jdet": 1.2, "Width": 0.6, "Error": 0.0, "1Subharmonic": 0.4, "Distance": 0.7999999999999999, "S/n": 148.92283192303543, "Error2": 0.0}, {"Jref": 1.2, "Jdet": 1.2, "Width": 0.6, "Error": 0.0, "1Subharmonic": 0.4, "Distance": 0.7999999999999999, "S/n": 152.9100546408687, "Error2": 0.0}, {"Jref": 1.2, "Jdet": 1.2, "Width": 0.6, "Error": 0.0, "1Subharmonic": 0.4, "Distance": 0.7999999999999999, "S/n": 155.70705799341306, "Error2": 0.0}, {"Jref": 1.2, "Jdet": 1.2, "Width": 0.6, "Error": 0.0, "1Subharmonic": 0.4, "Distance": 0.7999999999999999, "S/n": 155.79344771197412, "Error2": 0.0}, {"Jref": 1.2, "Jdet": 1.2, "Width": 0.6, "Error": 0.0, "1Subharmonic": 0.4, "Distance": 0.7999999999999999, "S/n": 164.2198235659129, "Error2": 0.0}, {"Jref": 1.2, "Jdet": 1.2, "Width": 0.6, "Error": 0.0, "1Subharmonic": 0.4, "Distance": 0.7999999999999999, "S/n": 165.17153790545913, "Error2": 0.0}, {"Jref": 1.2, "Jdet": 1.2, "Width": 0.6, "Error": 0.0, "1Subharmonic": 0.4, "Distance": 0.7999999999999999, "S/n": 166.63086389750097, "Error2": 0.0}, {"Jref": 1.2, "Jdet": 1.2, "Width": 0.6, "Error": 0.0, "1Subharmonic": 0.4, "Distance": 0.7999999999999999, "S/n": 174.14092098177488, "Error2": 0.0}, {"Jref": 1.2, "Jdet": 1.2, "Width": 0.6, "Error": 0.0, "1Subharmonic": 0.4, "Distance": 0.7999999999999999, "S/n": 173.2771256344062, "Error2": 0.0}, {"Jref": 1.2, "Jdet": 1.2, "Width": 0.6, "Error": 0.0, "1Subharmonic": 0.4, "Distance": 0.7999999999999999, "S/n": 176.9365282855331, "Error2": 0.0}, {"Jref": 1.2, "Jdet": 1.2, "Width": 0.6, "Error": 0.0, "1Subharmonic": 0.4, "Distance": 0.7999999999999999, "S/n": 181.65246207787428, "Error2": 0.0}, {"Jref": 1.2, "Jdet": 1.2, "Width": 0.6, "Error": 0.0, "1Subharmonic": 0.4, "Distance": 0.7999999999999999, "S/n": 183.34569617943464, "Error2": 0.0}, {"Jref": 1.2, "Jdet": 1.2, "Width": 0.6, "Error": 0.0, "1Subharmonic": 0.4, "Distance": 0.7999999999999999, "S/n": 189.35028643110667, "Error2": 0.0}, {"Jref": 1.2, "Jdet": 1.2, "Width": 0.6, "Error": 0.0, "1Subharmonic": 0.4, "Distance": 0.7999999999999999, "S/n": 195.5676860011239, "Error2": 0.0}, {"Jref": 1.2, "Jdet": 1.2, "Width": 0.6, "Error": 0.0, "1Subharmonic": 0.4, "Distance": 0.7999999999999999, "S/n": 192.76528515557146, "Error2": 0.0}, {"Jref": 1.2, "Jdet": 1.2, "Width": 0.6, "Error": 0.0, "1Subharmonic": 0.4, "Distance": 0.7999999999999999, "S/n": 195.36334922670227, "Error2": 0.0}, {"Jref": 1.2, "Jdet": 1.2, "Width": 0.6, "Error": 0.0, "1Subharmonic": 0.4, "Distance": 0.7999999999999999, "S/n": 196.2122369005127, "Error2": 0.0}, {"Jref": 1.2, "Jdet": 1.2, "Width": 0.6, "Error": 0.0, "1Subharmonic": 0.4, "Distance": 0.7999999999999999, "S/n": 205.85387864884248, "Error2": 0.0}, {"Jref": 1.2, "Jdet": 1.2, "Width": 0.6, "Error": 0.0, "1Subharmonic": 0.4, "Distance": 0.7999999999999999, "S/n": 208.32517364056542, "Error2": 0.0}, {"Jref": 1.2, "Jdet": 1.2, "Width": 0.6, "Error": 0.0, "1Subharmonic": 0.4, "Distance": 0.7999999999999999, "S/n": 209.91280176568404, "Error2": 0.0}, {"Jref": 1.2, "Jdet": 1.2, "Width": 0.6, "Error": 0.0, "1Subharmonic": 0.4, "Distance": 0.7999999999999999, "S/n": 209.99054126345956, "Error2": 0.0}, {"Jref": 1.2, "Jdet": 1.2, "Width": 0.6, "Error": 0.0, "1Subharmonic": 0.4, "Distance": 0.7999999999999999, "S/n": 215.85150138970917, "Error2": 0.0}, {"Jref": 1.2, "Jdet": 1.2, "Width": 0.6, "Error": 0.0, "1Subharmonic": 0.4, "Distance": 0.7999999999999999, "S/n": 216.81877757011543, "Error2": 0.0}, {"Jref": 1.2, "Jdet": 1.2, "Width": 0.6, "Error": 0.0, "1Subharmonic": 0.4, "Distance": 0.7999999999999999, "S/n": 221.3984471957224, "Error2": 0.0}, {"Jref": 1.2, "Jdet": 1.2, "Width": 0.6, "Error": 0.0, "1Subharmonic": 0.4, "Distance": 0.7999999999999999, "S/n": 226.06609063850811, "Error2": 0.0}, {"Jref": 1.2, "Jdet": 1.2, "Width": 0.6, "Error": 0.0, "1Subharmonic": 0.4, "Distance": 0.7999999999999999, "S/n": 229.4420791337499, "Error2": 0.0}, {"Jref": 1.2, "Jdet": 1.2, "Width": 0.6, "Error": 0.0, "1Subharmonic": 0.4, "Distance": 0.7999999999999999, "S/n": 233.4004096298792, "Error2": 0.0}, {"Jref": 1.2, "Jdet": 1.2, "Width": 0.6, "Error": 0.0, "1Subharmonic": 0.4, "Distance": 0.7999999999999999, "S/n": 236.02347085715647, "Error2": 0.0}, {"Jref": 1.2, "Jdet": 1.2, "Width": 0.6, "Error": 0.0, "1Subharmonic": 0.4, "Distance": 0.7999999999999999, "S/n": 235.7045584474251, "Error2": 0.0}, {"Jref": 1.2, "Jdet": 1.2, "Width": 0.6, "Error": 0.0, "1Subharmonic": 0.4, "Distance": 0.7999999999999999, "S/n": 247.99253645026496, "Error2": 0.0}, {"Jref": 1.2, "Jdet": 1.2, "Width": 0.6, "Error": 0.0, "1Subharmonic": 0.4, "Distance": 0.7999999999999999, "S/n": 244.97272706933163, "Error2": 0.0}, {"Jref": 1.2, "Jdet": 1.2, "Width": 0.6, "Error": 0.0, "1Subharmonic": 0.4, "Distance": 0.7999999999999999, "S/n": 236.54510816946794, "Error2": 0.0}, {"Jref": 1.2, "Jdet": 1.2, "Width": 0.6, "Error": 0.0, "1Subharmonic": 0.4, "Distance": 0.7999999999999999, "S/n": 254.58645142356917, "Error2": 0.0}, {"Jref": 1.2, "Jdet": 1.2, "Width": 0.6, "Error": 0.0, "1Subharmonic": 0.4, "Distance": 0.7999999999999999, "S/n": 252.87652801676623, "Error2": 0.0}, {"Jref": 1.2, "Jdet": 1.2, "Width": 0.6, "Error": 0.0, "1Subharmonic": 0.4, "Distance": 0.7999999999999999, "S/n": 252.2850504503953, "Error2": 0.0}, {"Jref": 1.2, "Jdet": 1.2, "Width": 0.6, "Error": 0.0, "1Subharmonic": 0.4, "Distance": 0.7999999999999999, "S/n": 253.87343116867828, "Error2": 0.0}, {"Jref": 1.2, "Jdet": 1.2, "Width": 0.6, "Error": 0.0, "1Subharmonic": 0.4, "Distance": 0.7999999999999999, "S/n": 261.57323952059, "Error2": 0.0}, {"Jref": 1.2, "Jdet": 1.2, "Width": 0.6, "Error": 0.0, "1Subharmonic": 0.4, "Distance": 0.7999999999999999, "S/n": 261.46938939490497, "Error2": 0.0}, {"Jref": 1.2, "Jdet": 1.2, "Width": 0.6, "Error": 0.0, "1Subharmonic": 0.4, "Distance": 0.7999999999999999, "S/n": 258.87994283359325, "Error2": 0.0}, {"Jref": 1.2, "Jdet": 1.2, "Width": 0.6, "Error": 0.0, "1Subharmonic": 0.4, "Distance": 0.7999999999999999, "S/n": 269.25840298998185, "Error2": 0.0}, {"Jref": 1.2, "Jdet": 1.2, "Width": 0.6, "Error": 0.0, "1Subharmonic": 0.4, "Distance": 0.7999999999999999, "S/n": 273.9494367579734, "Error2": 0.0}, {"Jref": 1.2, "Jdet": 1.2, "Width": 0.6, "Error": 0.0, "1Subharmonic": 0.4, "Distance": 0.7999999999999999, "S/n": 277.4131825856463, "Error2": 0.0}, {"Jref": 1.2, "Jdet": 1.2, "Width": 0.6, "Error": 0.0, "1Subharmonic": 0.4, "Distance": 0.7999999999999999, "S/n": 273.3479863397893, "Error2": 0.0}, {"Jref": 1.2, "Jdet": 1.2, "Width": 0.6, "Error": 0.0, "1Subharmonic": 0.4, "Distance": 0.7999999999999999, "S/n": 288.11168653056666, "Error2": 0.0}, {"Jref": 1.2, "Jdet": 1.2, "Width": 0.6, "Error": 0.0, "1Subharmonic": 0.4, "Distance": 0.7999999999999999, "S/n": 288.17896350407955, "Error2": 0.0}, {"Jref": 1.2, "Jdet": 1.2, "Width": 0.6, "Error": 0.0, "1Subharmonic": 0.4, "Distance": 0.7999999999999999, "S/n": 293.224417643571, "Error2": 0.0}, {"Jref": 1.2, "Jdet": 1.2, "Width": 0.6, "Error": 0.0, "1Subharmonic": 0.4, "Distance": 0.7999999999999999, "S/n": 285.28156404170375, "Error2": 0.0}, {"Jref": 1.2, "Jdet": 1.2, "Width": 0.6, "Error": 0.0, "1Subharmonic": 0.4, "Distance": 0.7999999999999999, "S/n": 302.93649702790674, "Error2": 0.0}, {"Jref": 1.2, "Jdet": 1.2, "Width": 0.6, "Error": 0.0, "1Subharmonic": 0.4, "Distance": 0.7999999999999999, "S/n": 298.5160270609822, "Error2": 0.0}, {"Jref": 1.2, "Jdet": 1.2, "Width": 0.6, "Error": 0.0, "1Subharmonic": 0.4, "Distance": 0.7999999999999999, "S/n": 309.12879957096004, "Error2": 0.0}, {"Jref": 1.2, "Jdet": 1.2, "Width": 0.6, "Error": 0.0, "1Subharmonic": 0.4, "Distance": 0.7999999999999999, "S/n": 305.1794130762731, "Error2": 0.0}, {"Jref": 1.2, "Jdet": 1.2, "Width": 0.6, "Error": 0.0, "1Subharmonic": 0.4, "Distance": 0.7999999999999999, "S/n": 308.504314594934, "Error2": 0.0}, {"Jref": 1.2, "Jdet": 1.2, "Width": 0.6, "Error": 0.0, "1Subharmonic": 0.4, "Distance": 0.7999999999999999, "S/n": 310.7707069607739, "Error2": 0.0}, {"Jref": 1.2, "Jdet": 1.2, "Width": 0.6, "Error": 0.0, "1Subharmonic": 0.4, "Distance": 0.7999999999999999, "S/n": 303.1775936330963, "Error2": 0.0}, {"Jref": 1.2, "Jdet": 1.2, "Width": 0.6, "Error": 0.0, "1Subharmonic": 0.4, "Distance": 0.7999999999999999, "S/n": 310.7626920800919, "Error2": 0.0}, {"Jref": 1.2, "Jdet": 1.2, "Width": 0.6, "Error": 0.0, "1Subharmonic": 0.4, "Distance": 0.7999999999999999, "S/n": 328.8103019805122, "Error2": 0.0}, {"Jref": 1.2, "Jdet": 1.2, "Width": 0.6, "Error": 0.0, "1Subharmonic": 0.4, "Distance": 0.7999999999999999, "S/n": 320.79755931953713, "Error2": 0.0}, {"Jref": 1.2, "Jdet": 1.2, "Width": 0.6, "Error": 0.0, "1Subharmonic": 0.4, "Distance": 0.7999999999999999, "S/n": 321.36326813561635, "Error2": 0.0}, {"Jref": 1.2, "Jdet": 1.2, "Width": 0.6, "Error": 0.0, "1Subharmonic": 0.4, "Distance": 0.7999999999999999, "S/n": 325.9600764744152, "Error2": 0.0}, {"Jref": 1.2, "Jdet": 1.2, "Width": 0.6, "Error": 0.0, "1Subharmonic": 0.4, "Distance": 0.7999999999999999, "S/n": 336.1787745750804, "Error2": 0.0}, {"Jref": 1.2, "Jdet": 1.2, "Width": 0.6, "Error": 0.0, "1Subharmonic": 0.4, "Distance": 0.7999999999999999, "S/n": 335.81276563915264, "Error2": 0.0}, {"Jref": 1.2, "Jdet": 1.2, "Width": 0.6, "Error": 0.0, "1Subharmonic": 0.4, "Distance": 0.7999999999999999, "S/n": 342.40361209689854, "Error2": 0.0}, {"Jref": 1.2, "Jdet": 1.2, "Width": 0.6, "Error": 0.0, "1Subharmonic": 0.4, "Distance": 0.7999999999999999, "S/n": 339.37631306683323, "Error2": 0.0}, {"Jref": 1.2, "Jdet": 1.2, "Width": 0.6, "Error": 0.0, "1Subharmonic": 0.4, "Distance": 0.7999999999999999, "S/n": 345.8438764585618, "Error2": 0.0}, {"Jref": 1.2, "Jdet": 1.2, "Width": 0.6, "Error": 0.0, "1Subharmonic": 0.4, "Distance": 0.7999999999999999, "S/n": 340.6045309968669, "Error2": 0.0}, {"Jref": 1.2, "Jdet": 1.2, "Width": 0.6, "Error": 0.0, "1Subharmonic": 0.4, "Distance": 0.7999999999999999, "S/n": 348.2180547818096, "Error2": 0.0}, {"Jref": 1.2, "Jdet": 1.2, "Width": 0.6, "Error": 0.0, "1Subharmonic": 0.4, "Distance": 0.7999999999999999, "S/n": 348.957222094607, "Error2": 0.0}, {"Jref": 1.2, "Jdet": 1.2, "Width": 0.6, "Error": 0.0, "1Subharmonic": 0.4, "Distance": 0.7999999999999999, "S/n": 347.3292224396283, "Error2": 0.0}, {"Jref": 1.2, "Jdet": 1.2, "Width": 0.6, "Error": 0.0, "1Subharmonic": 0.4, "Distance": 0.7999999999999999, "S/n": 354.8792209918414, "Error2": 0.0}, {"Jref": 1.2, "Jdet": 1.2, "Width": 0.6, "Error": 0.0, "1Subharmonic": 0.4, "Distance": 0.7999999999999999, "S/n": 366.5429566782422, "Error2": 0.0}, {"Jref": 1.2, "Jdet": 1.2, "Width": 0.6, "Error": 0.0, "1Subharmonic": 0.4, "Distance": 0.7999999999999999, "S/n": 352.8811162283356, "Error2": 0.0}, {"Jref": 1.2, "Jdet": 1.2, "Width": 0.6, "Error": 0.0, "1Subharmonic": 0.4, "Distance": 0.7999999999999999, "S/n": 365.5550284432982, "Error2": 0.0}, {"Jref": 1.2, "Jdet": 1.2, "Width": 0.6, "Error": 0.0, "1Subharmonic": 0.4, "Distance": 0.7999999999999999, "S/n": 373.7552043008229, "Error2": 0.0}, {"Jref": 1.2, "Jdet": 1.2, "Width": 0.6, "Error": 0.0, "1Subharmonic": 0.4, "Distance": 0.7999999999999999, "S/n": 370.78409725315714, "Error2": 0.0}, {"Jref": 1.2, "Jdet": 1.2, "Width": 0.6, "Error": 0.0, "1Subharmonic": 0.4, "Distance": 0.7999999999999999, "S/n": 375.7539013455843, "Error2": 0.0}, {"Jref": 1.2, "Jdet": 1.2, "Width": 0.6, "Error": 0.0, "1Subharmonic": 0.4, "Distance": 0.7999999999999999, "S/n": 376.1684213129493, "Error2": 0.0}, {"Jref": 1.2, "Jdet": 1.2, "Width": 0.6, "Error": 0.0, "1Subharmonic": 0.4, "Distance": 0.7999999999999999, "S/n": 374.731712439055, "Error2": 0.0}, {"Jref": 1.2, "Jdet": 1.2, "Width": 0.6, "Error": 0.0, "1Subharmonic": 0.4, "Distance": 0.7999999999999999, "S/n": 383.2688859277346, "Error2": 0.0}, {"Jref": 1.2, "Jdet": 1.2, "Width": 0.6, "Error": 0.0, "1Subharmonic": 0.4, "Distance": 0.7999999999999999, "S/n": 380.778012356101, "Error2": 0.0}, {"Jref": 1.2, "Jdet": 1.2, "Width": 0.6, "Error": 0.0, "1Subharmonic": 0.4, "Distance": 0.7999999999999999, "S/n": 396.1286706130016, "Error2": 0.0}, {"Jref": 1.2, "Jdet": 1.2, "Width": 0.6, "Error": 0.0, "1Subharmonic": 0.4, "Distance": 0.7999999999999999, "S/n": 390.70727624401366, "Error2": 0.0}, {"Jref": 1.2, "Jdet": 1.2, "Width": 0.6, "Error": 0.0, "1Subharmonic": 0.4, "Distance": 0.7999999999999999, "S/n": 400.8935665945742, "Error2": 0.0}, {"Jref": 1.2, "Jdet": 1.2, "Width": 0.6, "Error": 0.0, "1Subharmonic": 0.4, "Distance": 0.7999999999999999, "S/n": 402.16780164814855, "Error2": 0.0}, {"Jref": 1.2, "Jdet": 1.2, "Width": 0.6, "Error": 0.0, "1Subharmonic": 0.4, "Distance": 0.7999999999999999, "S/n": 398.4744718778794, "Error2": 0.0}, {"Jref": 1.2, "Jdet": 1.2, "Width": 0.6, "Error": 0.0, "1Subharmonic": 0.4, "Distance": 0.7999999999999999, "S/n": 408.25145104070106, "Error2": 0.0}, {"Jref": 1.2, "Jdet": 1.2, "Width": 0.6, "Error": 0.0, "1Subharmonic": 0.4, "Distance": 0.7999999999999999, "S/n": 411.42719208386086, "Error2": 0.0}, {"Jref": 1.2, "Jdet": 1.2, "Width": 0.6, "Error": 0.0, "1Subharmonic": 0.4, "Distance": 0.7999999999999999, "S/n": 402.95947509069117, "Error2": 0.0}, {"Jref": 1.2, "Jdet": 1.2, "Width": 0.6, "Error": 0.0, "1Subharmonic": 0.4, "Distance": 0.7999999999999999, "S/n": 419.7957134417623, "Error2": 0.0}, {"Jref": 1.2, "Jdet": 1.2, "Width": 0.6, "Error": 0.0, "1Subharmonic": 0.4, "Distance": 0.7999999999999999, "S/n": 416.66947470408786, "Error2": 0.0}, {"Jref": 1.2, "Jdet": 1.2, "Width": 0.6, "Error": 0.0, "1Subharmonic": 0.4, "Distance": 0.7999999999999999, "S/n": 414.7009789389886, "Error2": 0.0}, {"Jref": 1.2, "Jdet": 1.2, "Width": 0.6, "Error": 0.0, "1Subharmonic": 0.4, "Distance": 0.7999999999999999, "S/n": 427.08052847903014, "Error2": 0.0}, {"Jref": 1.2, "Jdet": 1.2, "Width": 0.6, "Error": 0.0, "1Subharmonic": 0.4, "Distance": 0.7999999999999999, "S/n": 429.70529491589656, "Error2": 0.0}, {"Jref": 1.2, "Jdet": 1.2, "Width": 0.6, "Error": 0.0, "1Subharmonic": 0.4, "Distance": 0.7999999999999999, "S/n": 425.3387470990127, "Error2": 0.0}, {"Jref": 1.2, "Jdet": 1.2, "Width": 0.6, "Error": 0.0, "1Subharmonic": 0.4, "Distance": 0.7999999999999999, "S/n": 425.6370365246847, "Error2": 0.0}, {"Jref": 1.2, "Jdet": 1.2, "Width": 0.6, "Error": 0.0, "1Subharmonic": 0.4, "Distance": 0.7999999999999999, "S/n": 432.3428685820744, "Error2": 0.0}, {"Jref": 1.2, "Jdet": 1.2, "Width": 0.6, "Error": 0.0, "1Subharmonic": 0.4, "Distance": 0.7999999999999999, "S/n": 435.48962057369033, "Error2": 0.0}, {"Jref": 1.2, "Jdet": 1.2, "Width": 0.6, "Error": 0.0, "1Subharmonic": 0.4, "Distance": 0.7999999999999999, "S/n": 456.22548688152636, "Error2": 0.0}, {"Jref": 1.2, "Jdet": 1.2, "Width": 0.6, "Error": 0.0, "1Subharmonic": 0.4, "Distance": 0.7999999999999999, "S/n": 469.5574758847527, "Error2": 0.0}, {"Jref": 1.2, "Jdet": 1.2, "Width": 0.6, "Error": 0.0, "1Subharmonic": 0.4, "Distance": 0.7999999999999999, "S/n": 446.7563783072393, "Error2": 0.0}, {"Jref": 1.2, "Jdet": 1.2, "Width": 0.6, "Error": 0.0, "1Subharmonic": 0.4, "Distance": 0.7999999999999999, "S/n": 449.7052110731614, "Error2": 0.0}, {"Jref": 1.2, "Jdet": 1.2, "Width": 0.6, "Error": 0.0, "1Subharmonic": 0.4, "Distance": 0.7999999999999999, "S/n": 456.930876208766, "Error2": 0.0}]